{
	"name": "Hardcore Theme",
	"type": "dark",
	"colors": {
		"focusBorder": "#3498db",
		"editor.background": "#080808",
		"editor.foreground": "#eeffff",
		"sideBar.background": "#000000",
		"sideBar.foreground": "#666666",
		"sideBarTitle.foreground": "#888888",
		"sideBarSectionHeader.background": "#000000",
		"activityBar.background": "#000000",
		"editorGroupHeader.noTabsBackground": "#000000",
		"editorGroupHeader.tabsBackground": "#000000",
		"editorGroup.emptyBackground": "#000000",
		"tab.inactiveBackground": "#000000",
		"tab.border": "#000000",
		"titleBar.activeBackground": "#000000",
		"titleBar.inactiveBackground": "#000000",
		"statusBar.background": "#000000",
		"statusBar.debuggingBackground": "#3498db",
		"activityBarBadge.background": "#000000",
		"menu.background": "#000000",
		"menu.selectionBackground": "#000000",
		"menu.separatorBackground": "#121212",
		"menubar.selectionBackground": "#000000",
		"list.activeSelectionBackground": "#000000",
		"list.activeSelectionForeground": "#3498db",
		"list.hoverBackground": "#000000",
		"list.hoverForeground": "#7ab8e1",
		"list.inactiveSelectionBackground": "#000000",
		"list.inactiveSelectionForeground": "#3498db",
		"list.filterMatchBackground": "#121212",
		"list.filterMatchBorder": "#3498db",
		"list.focusBackground": "#000000",
		"list.focusForeground": "#7ab8e1",
		"list.errorForeground": "#f92672",
		"list.warningForeground": "#9e6ffe",
		"listFilterWidget.background": "#121212",
		"listFilterWidget.outline": "#7ab8e1",
		"listFilterWidget.noMatchesOutline": "#63283E",
		"input.background": "#121212",
		"input.border": "#121212",
		"inputValidation.errorBackground": "#f92672",
		"inputValidation.errorBorder": "#f92672",
		"inputValidation.errorForeground": "#000000",
		"button.background": "#3498db",
		"textLink.foreground": "#3498db",
		"textLink.activeForeground": "#3498db",
		"dropdown.background": "#121212",
		"dropdown.listBackground": "#000000",
		"dropdown.border": "#121212",
		"badge.background": "#121212",
		"badge.foreground": "#7ab8e1",
		"panel.background": "#000000",
		"terminal.background": "#000000",
		"terminal.ansiBlack": "#1b1d1e",
		"terminal.ansiBlue": "#3498db",
		"terminal.ansiCyan": "#5e7175",
		"terminal.ansiGreen": "#a6e22e",
		"terminal.ansiMagenta": "#9e6ffe",
		"terminal.ansiRed": "#f92672",
		"terminal.ansiWhite": "#ccccc6",
		"terminal.ansiYellow": "#fd971f",
		"terminal.ansiBrightBlack": "#505354",
		"terminal.ansiBrightBlue": "#7ab8e1",
		"terminal.ansiBrightCyan": "#a3babf",
		"terminal.ansiBrightGreen": "#beed5f",
		"terminal.ansiBrightMagenta": "#9e6ffe",
		"terminal.ansiBrightRed": "#ff669d",
		"terminal.ansiBrightWhite": "#f8f8f2",
		"terminal.ansiBrightYellow": "#e6db74",
		"quickInput.background": "#000000",
		"quickInput.foreground": "#ccccc6",
		"quickInputTitle.background": "#000000",
		"pickerGroup.border": "#212121",
		"pickerGroup.foreground": "#3498db"
	},
	"tokenColors": "./Hardcore.tmTheme",
}